com/__init__.py
com/yootk/__init__.py
com/yootk/data.py
com/yootk/message.py
yootk.common-0.0.3.dist-info/METADATA
yootk.common-0.0.3.dist-info/WHEEL
yootk.common-0.0.3.dist-info/top_level.txt
yootk.common-0.0.3.dist-info/RECORD
